{
"corridors":[{"payeeCountry":"AUS","receiveCountry":"AUS","receiveCurrency":"USD","regular":false,"priority":true},{"payeeCountry":"AUS","receiveCountry":"AUS","receiveCurrency":"AUD","regular":true,"priority":true},{"payeeCountry":"CAN","receiveCountry":"CAN","receiveCurrency":"CAD","regular":true,"priority":true},{"payeeCountry":"CAN","receiveCountry":"CAN","receiveCurrency":"USD","regular":false,"priority":true},{"payeeCountry":"CHN","receiveCountry":"CHN","receiveCurrency":"CNY","regular":false,"priority":true},{"payeeCountry":"CHN","receiveCountry":"CHN","receiveCurrency":"USD","regular":false,"priority":true},{"payeeCountry":"DEU","receiveCountry":"DEU","receiveCurrency":"USD","regular":false,"priority":true},{"payeeCountry":"DEU","receiveCountry":"DEU","receiveCurrency":"EUR","regular":true,"priority":true},{"payeeCountry":"FRA","receiveCountry":"FRA","receiveCurrency":"EUR","regular":true,"priority":true},{"payeeCountry":"FRA","receiveCountry":"FRA","receiveCurrency":"USD","regular":false,"priority":true},{"payeeCountry":"GBR","receiveCountry":"GBR","receiveCurrency":"GBP","regular":true,"priority":true},{"payeeCountry":"GBR","receiveCountry":"GBR","receiveCurrency":"USD","regular":false,"priority":true},{"payeeCountry":"HKG","receiveCountry":"HKG","receiveCurrency":"USD","regular":false,"priority":true},{"payeeCountry":"HKG","receiveCountry":"HKG","receiveCurrency":"HKD","regular":true,"priority":true},{"payeeCountry":"IND","receiveCountry":"IND","receiveCurrency":"INR","regular":true,"priority":false},{"payeeCountry":"IND","receiveCountry":"IND","receiveCurrency":"USD","regular":false,"priority":true},{"payeeCountry":"JPN","receiveCountry":"JPN","receiveCurrency":"JPY","regular":false,"priority":true},{"payeeCountry":"JPN","receiveCountry":"JPN","receiveCurrency":"USD","regular":false,"priority":true},{"payeeCountry":"USA","receiveCountry":"USA","receiveCurrency":"USD","regular":true,"priority":true}],"processorSelectionCriteria":[{"receiveCountry":"AUS","receiveCurrency":"AUD","sendCurrency":"GBP"},{"receiveCountry":"GBR","receiveCurrency":"GBP","sendCurrency":"USD"},{"receiveCountry":"HKG","receiveCurrency":"HKD","sendCurrency":"USD"},{"receiveCountry":"CAN","receiveCurrency":"USD","sendCurrency":"USD"},{"receiveCountry":"FRA","receiveCurrency":"USD","sendCurrency":"USD"},{"receiveCountry":"DEU","receiveCurrency":"USD","sendCurrency":"USD"},{"receiveCountry":"HKG","receiveCurrency":"USD","sendCurrency":"USD"},{"receiveCountry":"AUS","receiveCurrency":"USD","sendCurrency":"USD"},{"receiveCountry":"CHN","receiveCurrency":"CNY","sendCurrency":"USD"},{"receiveCountry":"JPN","receiveCurrency":"JPY","sendCurrency":"USD"},{"receiveCountry":"CAN","receiveCurrency":"CAD","sendCurrency":"USD"},{"receiveCountry":"FRA","receiveCurrency":"EUR","sendCurrency":"USD"},{"receiveCountry":"DEU","receiveCurrency":"EUR","sendCurrency":"USD"},{"receiveCountry":"JPN","receiveCurrency":"USD","sendCurrency":"USD"},{"receiveCountry":"IND","receiveCurrency":"USD","sendCurrency":"USD"},{"receiveCountry":"IND","receiveCurrency":"INR","sendCurrency":"USD"},{"receiveCountry":"IND","receiveCurrency":"INR","sendCurrency":"USD"},{"receiveCountry":"GBR","receiveCurrency":"USD","sendCurrency":"USD"},{"receiveCountry":"USA","receiveCurrency":"USD","sendCurrency":"USD"},{"receiveCountry":"CHN","receiveCurrency":"USD","sendCurrency":"USD"}]}
